{
  "members": [
    {
      "member_id": "OPT-2025-00142",
      "name": "Sarah Johnson",
      "email": "sarah.johnson@email.com",
      "phone": "(555) 234-5678",
      "date_of_birth": "1985-03-15",
      "plan_type": "Premium",
      "plan_id": "OPT-PREMIUM-2025",
      "pcp": "Dr. Emily Chen, MD — Internal Medicine",
      "group_number": "GRP-TECH-4200",
      "employer": "TechCorp Industries",
      "enrollment_date": "2024-11-01",
      "status": "Active",
      "dependents": 2,
      "notes": "Chronic condition management — Type 2 diabetes. Uses insulin pump and CGM."
    },
    {
      "member_id": "OPT-2025-00287",
      "name": "Michael Rivera",
      "email": "m.rivera@email.com",
      "phone": "(555) 876-5432",
      "date_of_birth": "1978-07-22",
      "plan_type": "Basic",
      "plan_id": "OPT-BASIC-2025",
      "pcp": "Dr. James Patel, MD — Family Medicine",
      "group_number": "GRP-MFG-3100",
      "employer": "MidWest Manufacturing",
      "enrollment_date": "2025-01-01",
      "status": "Active",
      "dependents": 3,
      "notes": "Recent knee surgery — physical therapy approved through March 2025."
    },
    {
      "member_id": "OPT-2025-00415",
      "name": "Aisha Patel",
      "email": "aisha.patel@email.com",
      "phone": "(555) 345-6789",
      "date_of_birth": "1992-11-08",
      "plan_type": "Premium",
      "plan_id": "OPT-PREMIUM-2025",
      "pcp": "Dr. Lisa Wong, MD — OB/GYN",
      "group_number": "GRP-FIN-5500",
      "employer": "Eastern Financial Group",
      "enrollment_date": "2024-07-15",
      "status": "Active",
      "dependents": 0,
      "notes": "Fertility treatment approved — IVF cycle 1 scheduled Q1 2025."
    },
    {
      "member_id": "OPT-2025-00503",
      "name": "Robert Kim",
      "email": "robert.kim@email.com",
      "phone": "(555) 654-3210",
      "date_of_birth": "1965-01-30",
      "plan_type": "Basic",
      "plan_id": "OPT-BASIC-2025",
      "pcp": "Dr. Mark Thompson, DO — Internal Medicine",
      "group_number": "GRP-EDU-2200",
      "employer": "State University System",
      "enrollment_date": "2024-09-01",
      "status": "Active",
      "dependents": 1,
      "notes": "Hypertension management. Annual wellness visit due April 2025."
    },
    {
      "member_id": "OPT-2025-00671",
      "name": "Maria Gonzalez",
      "email": "maria.g@email.com",
      "phone": "(555) 789-0123",
      "date_of_birth": "1990-05-17",
      "plan_type": "Premium",
      "plan_id": "OPT-PREMIUM-2025",
      "pcp": "Dr. Rachel Adams, MD — Psychiatry",
      "group_number": "GRP-TECH-4200",
      "employer": "TechCorp Industries",
      "enrollment_date": "2025-01-01",
      "status": "Active",
      "dependents": 1,
      "notes": "Mental health services — weekly therapy sessions. Medication: Lexapro 10mg."
    },
    {
      "member_id": "OPT-2025-00099",
      "name": "David Chen",
      "email": "d.chen@email.com",
      "phone": "(555) 456-7890",
      "date_of_birth": "1970-12-03",
      "plan_type": "Basic",
      "plan_id": "OPT-BASIC-2025",
      "pcp": "Dr. Sarah Mitchell, MD — Internal Medicine",
      "group_number": "GRP-RET-1800",
      "employer": "National Retail Corp",
      "enrollment_date": "2024-06-01",
      "status": "Inactive",
      "dependents": 0,
      "notes": "Coverage terminated — left employer. COBRA eligible through June 2025."
    }
  ]
}
